fuzzmap/__init__.py
fuzzmap/__main__.py
fuzzmap/fuzzmap.py
fuzzmap/core/__init__.py
fuzzmap/core/cli/__init__.py
fuzzmap/core/cli/cli.py
fuzzmap/core/cli/parser.py
fuzzmap/core/controller/__init__.py
fuzzmap/core/controller/controller.py
fuzzmap/core/handler/__init__.py
fuzzmap/core/handler/advanced_payload.py
fuzzmap/core/handler/common_payload.py
fuzzmap/core/handler/param_recon.py
fuzzmap/core/handler/request_payload.py
fuzzmap/core/handler/config/sql_error.json
fuzzmap/core/handler/config/vuln_confidence.json
fuzzmap/core/handler/payloads/common_payload.json
fuzzmap/core/handler/payloads/sqli_payload.json
fuzzmap/core/handler/payloads/xss_payload.json
fuzzmap/core/logging/__init__.py
fuzzmap/core/logging/log.py
fuzzmap/core/util/__init__.py
fuzzmap/core/util/util.py
fuzzmap/doc/translations/README-KR.md
fuzzmap-0.2.2.dist-info/licenses/LICENSE
fuzzmap-0.2.2.dist-info/METADATA
fuzzmap-0.2.2.dist-info/WHEEL
fuzzmap-0.2.2.dist-info/entry_points.txt
fuzzmap-0.2.2.dist-info/top_level.txt
fuzzmap-0.2.2.dist-info/RECORD
