Metadata-Version: 2.4
Name: fuzzmap
Version: 0.2.2
Summary: FUZZmap is a web application vulnerability fuzzing tool designed to detect security flaws.
Home-page: https://github.com/offensive-tooling/fuzzmap
Author: Offensive Tooling (arrester, jhanks, mathe, arecia, hansowon)
Author-email: arresterloyal@gmail.com
Maintainer: Offensive Tooling
Maintainer-email: arresterloyal@gmail.com, jhanks1221@gmail.com, sosoeme8@gmail.com, syuwon2006@gmail.com, hansowon0601@gmail.com
Project-URL: Homepage, https://github.com/offensive-tooling/fuzzmap
Project-URL: Bug Tracker, https://github.com/offensive-tooling/fuzzmap/issues
Project-URL: Documentation, https://github.com/offensive-tooling/fuzzmap/wiki
Project-URL: Source Code, https://github.com/offensive-tooling/fuzzmap
Keywords: security,web,fuzzing,vulnerability,scanner
Classifier: Programming Language :: Python :: 3
Classifier: License :: OSI Approved :: MIT License
Classifier: Operating System :: OS Independent
Classifier: Development Status :: 4 - Beta
Classifier: Topic :: Security
Classifier: Topic :: Internet :: WWW/HTTP
Requires-Python: >=3.7
License-File: LICENSE
Requires-Dist: requests>=2.25.0
Requires-Dist: aiohttp>=3.7.4
Requires-Dist: beautifulsoup4>=4.9.3
Requires-Dist: playwright>=1.40.0
Requires-Dist: argparse
Dynamic: author
Dynamic: author-email
Dynamic: classifier
Dynamic: description
Dynamic: description-content-type
Dynamic: home-page
Dynamic: keywords
Dynamic: license-file
Dynamic: maintainer
Dynamic: maintainer-email
Dynamic: project-url
Dynamic: requires-dist
Dynamic: requires-python
Dynamic: summary
